shadow_scholar/__init__.py
shadow_scholar/__main__.py
shadow_scholar/cli.py
shadow_scholar/hello_world.py
shadow_scholar/app/__init__.py
shadow_scholar/app/chat_s2/__init__.py
shadow_scholar/app/chat_s2/library.py
shadow_scholar/app/chat_s2/llm.py
shadow_scholar/app/chat_s2/logging.py
shadow_scholar/app/chat_s2/main.py
shadow_scholar/app/chat_s2/search.py
shadow_scholar/app/chat_s2/res/logo.svg
shadow_scholar/app/chat_s2/res/style.css
shadow_scholar/app/galactica/__init__.py
shadow_scholar/app/galactica/_old.py
shadow_scholar/app/galactica/constants.py
shadow_scholar/app/galactica/convert_to_int8.py
shadow_scholar/app/galactica/example.png
shadow_scholar/app/galactica/galai_model.py
shadow_scholar/app/galactica/galai_parallel_policy.py
shadow_scholar/app/galactica/galai_utils.py
shadow_scholar/app/galactica/main.py
shadow_scholar/app/hello_world/__init__.py
shadow_scholar/app/hello_world/gradio.css
shadow_scholar/app/hello_world/main.py
shadow_scholar/app/hello_world/res/logo.png
shadow_scholar/app/hello_world/res/style.css
shadow_scholar/app/llama/__init__.py
shadow_scholar/app/llama/main.py
shadow_scholar/app/pdod/__init__.py
shadow_scholar/app/pdod/caches.py
shadow_scholar/app/pdod/datasets.py
shadow_scholar/app/pdod/main.py
shadow_scholar/app/pdod/mmda_utils.py
shadow_scholar/app/pdod/rankers.py
shadow_scholar/app/pdod/reg_utils.py
shadow_scholar/app/pdod/slicers.py
shadow_scholar/app/qa/__init__.py
shadow_scholar/app/qa/data.py
shadow_scholar/app/qa/main.py
shadow_scholar/collections/__init__.py
shadow_scholar/collections/athena.py
shadow_scholar/collections/queries/acl_anthology.sql
shadow_scholar/collections/queries/s2ag_abstracts.sql
shadow_scholar/collections/queries/s2ag_authors.sql
shadow_scholar/collections/queries/s2ag_citations.sql
shadow_scholar/collections/queries/s2ag_embeddings.sql
shadow_scholar/collections/queries/s2ag_paper_ids.sql
shadow_scholar/collections/queries/s2ag_papers.sql
shadow_scholar/collections/queries/s2ag_publication_venues.sql
shadow_scholar-0.6.1.dist-info/LICENSE
shadow_scholar-0.6.1.dist-info/METADATA
shadow_scholar-0.6.1.dist-info/WHEEL
shadow_scholar-0.6.1.dist-info/entry_points.txt
shadow_scholar-0.6.1.dist-info/top_level.txt
shadow_scholar-0.6.1.dist-info/RECORD
