Metadata-Version: 2.1
Name: shadow-scholar
Version: 0.6.1
Summary: 🎓🕶️ A collection of utilities and demos from the Semantic Scholar Research Team 🕶️🎓
Author-email: Luca Soldaini <lucas@allenai.org>
License: Apache-2.0
Project-URL: Homepage, https://github.com/allenai/shadow-scholar
Project-URL: Source, https://github.com/allenai/shadow-scholar
Project-URL: Tracker, https://github.com/allenai/shadow-scholar/issues
Classifier: Development Status :: 3 - Alpha
Classifier: Typing :: Typed
Requires-Python: >=3.8
License-File: LICENSE
Requires-Dist: necessary (>=0.4.2)
Requires-Dist: typing-extensions (>=4.0.0)
Requires-Dist: platformdirs (>=2.4.0)
Requires-Dist: cachetools (>=4.2.4)
Provides-Extra: dev
Requires-Dist: black (>=22.6.0) ; extra == 'dev'
Requires-Dist: isort (>=5.10.1) ; extra == 'dev'
Requires-Dist: mypy (>=0.971) ; extra == 'dev'
Requires-Dist: pytest (>=5.2) ; extra == 'dev'
Requires-Dist: ipython (>=8.4.0) ; extra == 'dev'
Requires-Dist: autopep8 (>=1.7.0) ; extra == 'dev'
Requires-Dist: flake8 (>=5.0) ; extra == 'dev'
Requires-Dist: ipdb (>=0.13.0) ; extra == 'dev'
Requires-Dist: flake8-pyi (>=22.8.1) ; extra == 'dev'
Requires-Dist: Flake8-pyproject (>=1.1.0) ; extra == 'dev'
